{
  "galleries": [
    {
      "uid": "a160dd71-beac-4c6d-928d-dc7c69f7f6cf",
      "name": "No Tan Retro",
      "description": "My online gallery",
      "visible": false,
      "images": 1,
      "timestamp": 1761609162061
    },
    {
      "uid": "5a5b2dca-1055-4066-a4f7-5a216d40fb70",
      "name": "Fiesta EPA!",
      "description": "My online gallery",
      "images": 0,
      "visible": false,
      "timestamp": 1761609162061
    },
    {
      "uid": "43347638-0060-4c11-a8cb-af6eaad73b87",
      "name": "FDP",
      "description": "My online gallery",
      "images": 0,
      "visible": false,
      "timestamp": 1761609162061
    },
    {
      "uid": "0e75a2a3-a53f-491d-a2ab-8e879849ce4e",
      "name": "Noche buena",
      "description": "My online gallery",
      "images": 0,
      "visible": true,
      "timestamp": 1761609350417
    }
  ]
}